ndslib/__init__.py
ndslib/config.py
ndslib/data.py
ndslib/image.py
ndslib/version.py
ndslib/viz.py
ndslib/templates/nds.mplstyle
ndslib-0.6.1.dist-info/LICENSE
ndslib-0.6.1.dist-info/METADATA
ndslib-0.6.1.dist-info/WHEEL
ndslib-0.6.1.dist-info/top_level.txt
ndslib-0.6.1.dist-info/RECORD
