Metadata-Version: 2.1
Name: ndslib
Version: 0.6.1
Summary: Utility functions for Neuroimaging and Data Science
Home-page: https://github.com/neuroimaging-data-science/ndslib
Download-URL: https://github.com/neuroimaging-data-science/ndslib
Author: Ariel Rokem and Tal Yarkoni
Author-email: arokem@gmail.com
Maintainer: Ariel Rokem
Maintainer-email: arokem@gmail.com
License: MIT License
Platform: OS Independent
Classifier: Development Status :: 3 - Alpha
Classifier: Environment :: Console
Classifier: Intended Audience :: Science/Research
Classifier: License :: OSI Approved :: MIT License
Classifier: Operating System :: OS Independent
Classifier: Programming Language :: Python
Classifier: Topic :: Scientific/Engineering
Requires-Python: >=3.10
License-File: LICENSE
Requires-Dist: numpy
Requires-Dist: nibabel
Requires-Dist: ipython
Requires-Dist: jupyter
Requires-Dist: pandas
Requires-Dist: seaborn
Requires-Dist: sphinx
Requires-Dist: numpydoc
Requires-Dist: scikit-image
Requires-Dist: scikit-learn
Requires-Dist: viznet
Requires-Dist: nilearn
Requires-Dist: matplotlib
Requires-Dist: sphinx-rtd-theme
Requires-Dist: sphinx-copybutton
Requires-Dist: sphinx-math-dollar
